pymindergas/__init__.py
pymindergas-0.1.12.dist-info/COPYING
pymindergas-0.1.12.dist-info/METADATA
pymindergas-0.1.12.dist-info/WHEEL
pymindergas-0.1.12.dist-info/top_level.txt
pymindergas-0.1.12.dist-info/RECORD
